DSD Project + CEP/CEP/CEP.srcs/sources_1/new/data_memory.v
`timescale 1ns / 1ps
module data_memory (
    input wire clk, mem_read, mem_write,
    input wire [31:0] addr, write_data,
    output reg [31:0] read_data
);
    reg [31:0] mem [0:1023];
    integer i;
    initial
        for (i=0; i<1024; i=i+1)
            mem[i] = 32'h00000000;
    
    // combinational read
    always @(*)
        begin
            if (mem_read)
                read_data = mem[addr[11:2]];
            else
                read_data = 32'h00000000;
        end
    
    // synchronous write
    always @(posedge clk)
        begin
            if (mem_write)
                mem[addr[11:2]] <= write_data;
        end
endmodule

DSD Project + CEP/CEP/CEP.srcs/sources_1/new/alu.v
`timescale 1ns / 1ps
module alu (
    input wire [31:0] a, b,
    input wire [2:0] alu_control,
    output reg [31:0] result,
    output reg zero
);
    always @(*)
        begin
            case (alu_control)
                3'b000: result = a + b;           // add
                3'b001: result = a - b;           // sub
                3'b010: result = a & b;           // and
                3'b011: result = a | b;           // or
                3'b100: result = ($signed(a) < $signed(b)) ? 1 : 0; // slt
                default: result = 32'h00000000;
            endcase
            zero = (result == 32'h00000000);
        end
endmodule

DSD Project + CEP/CEP/CEP.srcs/sources_1/new/alu_control.v
`timescale 1ns / 1ps
module alu_control (
    input wire [1:0] alu_op,
    input wire [5:0] funct,
    output reg [2:0] alu_control
);
    always @(*)
        begin
            case (alu_op)
                2'b00: alu_control = 3'b000;      // lw/sw/addi
                2'b01: alu_control = 3'b001;      // beq (subtract)
                2'b10:
                begin                       // R-type
                
                    case (funct)
                        6'b100000: alu_control = 3'b000; // add
                        6'b100010: alu_control = 3'b001; // sub
                        6'b100100: alu_control = 3'b010; // and
                        6'b100101: alu_control = 3'b011; // or
                        6'b101010: alu_control = 3'b100; // slt
                        default:   alu_control = 3'b000;
                    endcase
                end
                
                default: alu_control = 3'b000;
            endcase
        end
endmodule

DSD Project + CEP/CEP/CEP.srcs/sources_1/new/sign_extend.v
`timescale 1ns / 1ps
module sign_extend (
    input wire [15:0] imm16,
    output reg [31:0] imm32
);
    always @(*)
        imm32 = {{16{imm16[15]}}, imm16};
endmodule

DSD Project + CEP/CEP/CEP.srcs/sources_1/new/register_file.v
`timescale 1ns / 1ps
// register_file.v (with third read port for display)
module register_file (
    input wire clk, reg_write,
    input wire [4:0] read_reg1, read_reg2,
    input wire [4:0] read_reg3,       // NEW: for display
    input wire [4:0] write_reg,
    input wire [31:0] write_data,
    output reg [31:0] read_data1, read_data2,
    output reg [31:0] read_data3       // NEW: display data
);
    reg [31:0] regs [0:31];
    integer i;
    
    initial
        begin
            for (i=0; i<32; i=i+1)
                regs[i] = 32'h00000000;
        end
    
    always @(*)
        begin
            read_data1 = (read_reg1 == 5'b0) ? 32'h00000000 : regs[read_reg1];
            read_data2 = (read_reg2 == 5'b0) ? 32'h00000000 : regs[read_reg2];
            read_data3 = (read_reg3 == 5'b0) ? 32'h00000000 : regs[read_reg3];
        end
    
    always @(posedge clk)
        begin
            if (reg_write && write_reg != 5'b0)
                regs[write_reg] <= write_data;
        end
endmodule

DSD Project + CEP/CEP/CEP.srcs/sources_1/new/control_unit.v
`timescale 1ns / 1ps
module control_unit (
    input wire [5:0] opcode,
    output reg reg_dst, alu_src, mem_to_reg, reg_write, mem_read, mem_write, branch, jump,
    output reg [1:0] alu_op,
    output reg illegal   // error detection
);
    always @(*)
        begin
            // default values
            reg_dst = 1'b0;
            alu_src = 1'b0;
            mem_to_reg = 1'b0;
            reg_write = 1'b0;
            mem_read = 1'b0;
            mem_write = 1'b0;
            branch = 1'b0;
            jump = 1'b0;
            alu_op = 2'b00;
            illegal = 1'b0;
        
            case (opcode)
                6'b000000:
                begin  // R-type
                    reg_dst = 1'b1;
                    reg_write = 1'b1;
                    alu_op = 2'b10;
                end
            
                6'b001000:
                begin  // addi
                    alu_src = 1'b1;
                    reg_write = 1'b1;
                    alu_op = 2'b00;
                end
    
                6'b100011:
                begin  // lw
                    alu_src = 1'b1;
                    mem_to_reg = 1'b1;
                    reg_write = 1'b1;
                    mem_read = 1'b1;
                    alu_op = 2'b00;
                end
                
                6'b101011:
                begin  // sw
                    alu_src = 1'b1;
                    mem_write = 1'b1;
                    alu_op = 2'b00;
                end
                
                6'b000100:
                begin  // beq
                    branch = 1'b1;
                    alu_op = 2'b01;
                end
                
                6'b000010:
                begin  // j
                    jump = 1'b1;
                end
            
                default: illegal = 1'b1;
            endcase
        end
endmodule

DSD Project + CEP/CEP/CEP.srcs/sources_1/new/instruction_memory.v
`timescale 1ns / 1ps
module instruction_memory (
    input wire [31:0] addr,
    output reg [31:0] instr
);
    // 1024 words of 32-bit instruction memory
    reg [31:0] mem [0:1023];
    integer i;
    // Initialize with a sample program (see section 6 for details)
    initial
        begin
            mem[0] = 32'h20080005;
            mem[1] = 32'h2009000A;
            mem[2] = 32'h012A5020;
            mem[3] = 32'h012A5822;
            mem[4] = 32'h01096024;
            mem[5] = 32'h01096825;
            mem[6] = 32'h0109702A;
            mem[7] = 32'hAD0A0000;
            mem[8] = 32'h8D070000;
            mem[9] = 32'h11290002;
            mem[10] = 32'h0800000B;   // j to word address 11 (44 decimal)
            mem[11]= 32'h00000020;   
            
            // fill rest with nop
            for (i=12; i<1024; i = i + 1)
                mem[i] = 32'h00000000;
        end
    
    always @(*)
        begin
            instr = mem[addr[11:2]];  // word-aligned access
        end
endmodule

DSD Project + CEP/CEP/CEP.srcs/sources_1/new/program_counter.v
`timescale 1ns / 1ps
module pc (
    input wire clk, reset,
    input wire [31:0] next_pc,
    output reg [31:0] pc
);
    always @(posedge clk or posedge reset)
        begin
            if (reset)
                pc <= 32'h00000000;
            else
                pc <= next_pc;
        end
endmodule

DSD Project + CEP/CEP/CEP.srcs/sources_1/new/mips_core.v
`timescale 1ns / 1ps
module mips_core (
    input wire clk, reset,
    input wire [4:0] reg_sel,          // NEW: selects which register to read for display
    output wire [31:0] pc_out, alu_result, mem_read_data, write_data_to_mem,
    output wire [31:0] reg_display_out, // NEW: value of register selected by reg_sel
    output reg illegal_inst, halt
);
    wire [31:0] pc, next_pc, instr;
    wire [31:0] read_data1, read_data2, imm32, alu_in2, alu_out, mem_readdata;
    wire [4:0] write_reg;
    wire [2:0] alu_ctrl;
    wire zero;
    wire reg_dst, alu_src, mem_to_reg, reg_write, mem_read, mem_write, branch, jump;
    wire [1:0] alu_op;
    wire illegal_ctrl;
    
    // PC
    pc pc_inst (.clk(clk), .reset(reset), .next_pc(next_pc), .pc(pc));
    
    // Instruction Memory
    instruction_memory imem (.addr(pc), .instr(instr));
    
    // Control Unit
    control_unit cu (.opcode(instr[31:26]), .reg_dst(reg_dst), .alu_src(alu_src),
                     .mem_to_reg(mem_to_reg), .reg_write(reg_write), .mem_read(mem_read),
                     .mem_write(mem_write), .branch(branch), .jump(jump), .alu_op(alu_op),
                     .illegal(illegal_ctrl));
    
    // Register File
    register_file rf (.clk(clk), .reg_write(reg_write), .read_reg1(instr[25:21]),
                      .read_reg2(instr[20:16]), .read_reg3(reg_sel), // from top-level input
                      .write_reg(write_reg), .write_data(mem_to_reg ? mem_readdata : alu_out),
                      .read_data1(read_data1), .read_data2(read_data2),
                      .read_data3(reg_display_out) // connect to output
                      );
    
    assign write_reg = reg_dst ? instr[15:11] : instr[20:16];
    
    // Sign Extend & ALU Mux
    sign_extend sext (.imm16(instr[15:0]), .imm32(imm32));
    assign alu_in2 = alu_src ? imm32 : read_data2;
    
    // ALU Control
    alu_control alu_ctrl_inst (.alu_op(alu_op), .funct(instr[5:0]), .alu_control(alu_ctrl));
    alu alu_inst (.a(read_data1), .b(alu_in2), .alu_control(alu_ctrl),
                  .result(alu_out), .zero(zero));
    
    // Data Memory
    data_memory dmem (.clk(clk), .mem_read(mem_read), .mem_write(mem_write),
                      .addr(alu_out), .write_data(read_data2), .read_data(mem_readdata));
    
    // Next PC Logic
    wire [31:0] pc_plus4 = pc + 4;
    wire [31:0] branch_target = pc_plus4 + (imm32 << 2);
    wire [31:0] jump_target = {pc_plus4[31:28], instr[25:0], 2'b00};
    wire branch_taken = branch & zero;
    
    assign next_pc = jump ? jump_target :
                     (branch_taken ? branch_target : pc_plus4);
    
    // Outputs for Debugging / Display
    assign pc_out = pc;
    assign alu_result = alu_out;
    assign mem_read_data = mem_readdata;
    assign write_data_to_mem = read_data2;
    
    // Illegal instruction detection and halt (simple counter stop)
    always @(posedge clk or posedge reset)
        begin
            if (reset)
                begin
                    illegal_inst <= 1'b0;
                    halt <= 1'b0;
                end
            else if (illegal_ctrl)
                begin
                    illegal_inst <= 1'b1;
                    halt <= 1'b1;
                end
            else if (pc == 32'h0000002C)
                begin   // example end address
                    halt <= 1'b1;
                end
        end
endmodule

DSD Project + CEP/CEP/CEP.srcs/sim_1/new/mips_tb.v
`timescale 1ns/1ps
module mips_tb;
    reg clk, reset;
    reg [4:0] reg_sel;           // NEW: select register for display (unused in sim)
    wire [31:0] pc, alu_out, reg_display;
    wire illegal, halt;
    
    // Instantiate the modified mips_core
    mips_core uut (
        .clk(clk),
        .reset(reset),
        .reg_sel(reg_sel),          // connect to a driver
        .reg_display_out(reg_display),
        .pc_out(pc),
        .alu_result(alu_out),
        .mem_read_data(),
        .write_data_to_mem(),
        .illegal_inst(illegal),
        .halt(halt)
    );
    
    always #5 clk = ~clk;   // 100 MHz clock
    
    initial
        begin
            $dumpfile("mips_tb.vcd");
            $dumpvars(0, mips_tb);
            clk = 0;
            reset = 1;
            reg_sel = 5'b00000;    // default to register 0
            #15 
            reset = 0;
            #500
            $finish();
        end
    
    initial
        begin
            $monitor("Time=%0t PC=%h ALU_out=%h Illegal=%b Halt=%b Reg_display=%h",
                $time, pc, alu_out, illegal, halt, reg_display);
        end
endmodule

DSD Project + CEP/CEP/CEP.sim/sim_1/behav/xsim/mips_tb.vcd
$date
   Sun May 31 17:00:19 2026
$end
$version
  2018.2
$end
$timescale
  1ps
$end
$scope module mips_tb $end
$var reg 1 ! clk $end
$var reg 1 " reset $end
$var reg 5 # reg_sel [4:0] $end
$var wire 32 $ pc [31:0] $end
$var wire 32 % alu_out [31:0] $end
$var wire 32 & reg_display [31:0] $end
$var wire 1 ' illegal $end
$var wire 1 ( halt $end
$scope module uut $end
$var wire 1 ) clk $end
$var wire 1 * reset $end
$var wire 5 + reg_sel [4:0] $end
$var wire 32 $ pc_out [31:0] $end
$var wire 32 % alu_result [31:0] $end
$var wire 32 , mem_read_data [31:0] $end
$var wire 32 - write_data_to_mem [31:0] $end
$var wire 32 & reg_display_out [31:0] $end
$var reg 1 . illegal_inst $end
$var reg 1 / halt $end
$var wire 32 0 pc [31:0] $end
$var wire 32 1 next_pc [31:0] $end
$var wire 32 2 instr [31:0] $end
$var wire 32 3 read_data1 [31:0] $end
$var wire 32 4 read_data2 [31:0] $end
$var wire 32 5 imm32 [31:0] $end
$var wire 32 6 alu_in2 [31:0] $end
$var wire 32 7 alu_out [31:0] $end
$var wire 32 8 mem_readdata [31:0] $end
$var wire 5 9 write_reg [4:0] $end
$var wire 3 : alu_ctrl [2:0] $end
$var wire 1 ; zero $end
$var wire 1 < reg_dst $end
$var wire 1 = alu_src $end
$var wire 1 > mem_to_reg $end
$var wire 1 ? reg_write $end
$var wire 1 @ mem_read $end
$var wire 1 A mem_write $end
$var wire 1 B branch $end
$var wire 1 C jump $end
$var wire 2 D alu_op [1:0] $end
$var wire 1 E illegal_ctrl $end
$var wire 32 F pc_plus4 [31:0] $end
$var wire 32 G branch_target [31:0] $end
$var wire 32 H jump_target [31:0] $end
$var wire 1 I branch_taken $end
$scope module pc_inst $end
$var wire 1 ) clk $end
$var wire 1 * reset $end
$var wire 32 1 next_pc [31:0] $end
$var reg 32 J pc [31:0] $end
$upscope $end
$scope module imem $end
$var wire 32 0 addr [31:0] $end
$var reg 32 K instr [31:0] $end
$var integer 32 L i $end
$upscope $end
$scope module cu $end
$var wire 6 M opcode [5:0] $end
$var reg 1 N reg_dst $end
$var reg 1 O alu_src $end
$var reg 1 P mem_to_reg $end
$var reg 1 Q reg_write $end
$var reg 1 R mem_read $end
$var reg 1 S mem_write $end
$var reg 1 T branch $end
$var reg 1 U jump $end
$var reg 2 V alu_op [1:0] $end
$var reg 1 W illegal $end
$upscope $end
$scope module rf $end
$var wire 1 ) clk $end
$var wire 1 ? reg_write $end
$var wire 5 X read_reg1 [4:0] $end
$var wire 5 Y read_reg2 [4:0] $end
$var wire 5 + read_reg3 [4:0] $end
$var wire 5 9 write_reg [4:0] $end
$var wire 32 Z write_data [31:0] $end
$var reg 32 [ read_data1 [31:0] $end
$var reg 32 \ read_data2 [31:0] $end
$var reg 32 ] read_data3 [31:0] $end
$var integer 32 ^ i $end
$upscope $end
$scope module sext $end
$var wire 16 _ imm16 [15:0] $end
$var reg 32 ` imm32 [31:0] $end
$upscope $end
$scope module alu_ctrl_inst $end
$var wire 2 D alu_op [1:0] $end
$var wire 6 a funct [5:0] $end
$var reg 3 b alu_control [2:0] $end
$upscope $end
$scope module alu_inst $end
$var wire 32 3 a [31:0] $end
$var wire 32 6 b [31:0] $end
$var wire 3 : alu_control [2:0] $end
$var reg 32 c result [31:0] $end
$var reg 1 d zero $end
$upscope $end
$scope module dmem $end
$var wire 1 ) clk $end
$var wire 1 @ mem_read $end
$var wire 1 A mem_write $end
$var wire 32 7 addr [31:0] $end
$var wire 32 4 write_data [31:0] $end
$var reg 32 e read_data [31:0] $end
$var integer 32 f i $end
$upscope $end
$upscope $end
$upscope $end
$enddefinitions $end
#0
$dumpvars
0!
1"
b0 #
b0 $
b101 %
b0 &
0'
0(
0)
1*
b0 +
b0 ,
b0 -
0.
0/
b0 0
b100 1
b100000000010000000000000000101 2
b0 3
b0 4
b101 5
b101 6
b101 7
b0 8
b1000 9
b0 :
0;
0<
1=
0>
1?
0@
0A
0B
0C
b0 D
0E
b100 F
b11000 G
b1000000000000000010100 H
0I
b0 J
b100000000010000000000000000101 K
b10000000000 L
b1000 M
0N
1O
0P
1Q
0R
0S
0T
0U
b0 V
0W
b0 X
b1000 Y
b101 Z
b0 [
b0 \
b0 ]
b100000 ^
b101 _
b101 `
b101 a
b0 b
b101 c
0d
b0 e
b10000000000 f
$end
#5000
1!
1)
b101 -
b101 4
b101 6
b0 [
b101 \
b0 ]
#10000
0!
0)
#15000
1!
0"
b100 $
b1010 %
1)
0*
b0 -
b100 0
b1000 1
b100000000010010000000000001010 2
b0 4
b1010 5
b1010 6
b1010 7
b1001 9
b1000 F
b110000 G
b1001000000000000101000 H
b100 J
b100000000010010000000000001010 K
b1000 M
b0 X
b1001 Y
b1010 Z
b0 [
b0 \
b0 ]
b1010 _
b1010 `
b1010 a
b0 b
b1010 c
0d
b0 e
#20000
0!
0)
#25000
1!
b1000 $
1)
b0 -
b1000 0
b1100 1
b1001010100101000000100000 2
b1010 3
b0 4
b101000000100000 5
b0 6
b1010 9
1<
0=
b10 D
b1100 F
b10100000010001100 G
b100101010010100000010000000 H
b1000 J
b1001010100101000000100000 K
b0 M
1N
0O
0P
1Q
0R
0S
0T
0U
b10 V
0W
b1001 X
b1010 Y
b1010 [
b0 \
b0 ]
b101000000100000 _
b101000000100000 `
b100000 a
b0 b
b1010 c
0d
#30000
0!
0)
#35000
1!
b1100 $
b0 %
1)
b1010 -
b1100 0
b10000 1
b1001010100101100000100010 2
b1010 4
b101100000100010 5
b1010 6
b0 7
b1011 9
b1 :
1;
b10000 F
b10110000010011000 G
b100101010010110000010001000 H
0I
b1100 J
b1001010100101100000100010 K
b0 M
b1001 X
b1010 Y
b0 Z
b1010 [
b1010 \
b0 ]
b101100000100010 _
b101100000100010 `
b100010 a
b1 b
b0 c
1d
b0 e
#40000
0!
0)
#45000
1!
b10000 $
1)
b10000 0
b10100 1
b1000010010110000000100100 2
b101 3
b110000000100100 5
b1010 6
b1100 9
b10 :
b10100 F
b11000000010100100 G
b100001001011000000010010000 H
b10000 J
b1000010010110000000100100 K
b0 M
b1000 X
b1001 Y
b101 [
b1010 \
b0 ]
b110000000100100 _
b110000000100100 `
b100100 a
b10 b
b0 c
1d
#50000
0!
0)
#55000
1!
b10100 $
b1111 %
1)
b10100 0
b11000 1
b1000010010110100000100101 2
b110100000100101 5
b1010 6
b1111 7
b1101 9
b11 :
0;
b11000 F
b11010000010101100 G
b100001001011010000010010100 H
0I
b10100 J
b1000010010110100000100101 K
b0 M
b1000 X
b1001 Y
b1111 Z
b110100000100101 _
b110100000100101 `
b100101 a
b11 b
b1111 c
0d
b0 e
#60000
0!
0)
#65000
1!
b11000 $
b1 %
1)
b11000 0
b11100 1
b1000010010111000000101010 2
b111000000101010 5
b1010 6
b1 7
b1110 9
b100 :
b11100 F
b11100000011000100 G
b100001001011100000010101000 H
b11000 J
b1000010010111000000101010 K
b0 M
b1000 X
b1001 Y
b1 Z
b101 [
b1010 \
b0 ]
b111000000101010 _
b111000000101010 `
b101010 a
b100 b
b1 c
0d
b0 e
#70000
0!
0)
#75000
1!
b11100 $
b101 %
1)
b11100 0
b100000 1
b10101101000010100000000000000000 2
b0 5
b0 6
b101 7
b1010 9
b0 :
0<
1=
0?
1A
b0 D
b100000 F
b100000 G
b100001010000000000000000000 H
b11100 J
b10101101000010100000000000000000 K
b101011 M
0N
1O
0P
0Q
0R
1S
0T
0U
b0 V
0W
b1000 X
b1010 Y
b101 Z
b101 [
b1010 \
b0 ]
b0 _
b0 `
b0 a
b0 b
b101 c
0d
b0 e
#80000
0!
0)
#85000
1!
b100000 $
1)
b1010 ,
b0 -
b100000 0
b100100 1
b10001101000001110000000000000000 2
b0 4
b0 6
b1010 8
b111 9
1=
1>
1?
1@
0A
b100100 F
b100100 G
b100000111000000000000000000 H
b100000 J
b10001101000001110000000000000000 K
b100011 M
0N
1O
1P
1Q
1R
0S
0T
0U
b0 V
0W
b1000 X
b111 Y
b1010 Z
b101 [
b0 \
b0 ]
b0 _
b0 a
b1010 e
#90000
0!
0)
#95000
1!
b100100 $
b0 %
1)
b0 ,
b1010 -
b100100 0
b110000 1
b10001001010010000000000000010 2
b1010 3
b1010 4
b10 5
b1010 6
b0 7
b0 8
b1001 9
b1 :
1;
0=
0>
0?
0@
1B
b1 D
b101000 F
b110000 G
b100101001000000000000001000 H
1I
b100100 J
b10001001010010000000000000010 K
b100 M
0N
0O
0P
0Q
0R
0S
1T
0U
b1 V
0W
b1001 X
b1001 Y
b0 Z
b1010 [
b1010 \
b0 ]
b10 _
b10 `
b10 a
b1 b
b0 c
1d
b0 e
#100000
0!
0)
#105000
1!
b110000 $
1)
b0 -
b110000 0
b110100 1
b0 2
b0 3
b0 4
b0 5
b0 6
b0 9
b0 :
1<
1?
0B
b10 D
b110100 F
b110100 G
b0 H
0I
b110000 J
b0 K
b0 M
1N
0O
0P
1Q
0R
0S
0T
0U
b10 V
0W
b0 X
b0 Y
b0 [
b0 \
b0 ]
b0 _
b0 `
b0 a
b0 b
b0 c
1d
#110000
0!
0)
#115000
1!
b110100 $
1)
b110100 0
b111000 1
b111000 F
b111000 G
b110100 J
b0 K
#120000
0!
0)
#125000
1!
b111000 $
1)
b111000 0
b111100 1
b111100 F
b111100 G
b111000 J
b0 K
#130000
0!
0)
#135000
1!
b111100 $
1)
b111100 0
b1000000 1
b1000000 F
b1000000 G
b111100 J
b0 K
#140000
0!
0)
#145000
1!
b1000000 $
1)
b1000000 0
b1000100 1
b1000100 F
b1000100 G
b1000000 J
b0 K
#150000
0!
0)
#155000
1!
b1000100 $
1)
b1000100 0
b1001000 1
b1001000 F
b1001000 G
b1000100 J
b0 K
#160000
0!
0)
#165000
1!
b1001000 $
1)
b1001000 0
b1001100 1
b1001100 F
b1001100 G
b1001000 J
b0 K
#170000
0!
0)
#175000
1!
b1001100 $
1)
b1001100 0
b1010000 1
b1010000 F
b1010000 G
b1001100 J
b0 K
#180000
0!
0)
#185000
1!
b1010000 $
1)
b1010000 0
b1010100 1
b1010100 F
b1010100 G
b1010000 J
b0 K
#190000
0!
0)
#195000
1!
b1010100 $
1)
b1010100 0
b1011000 1
b1011000 F
b1011000 G
b1010100 J
b0 K
#200000
0!
0)
#205000
1!
b1011000 $
1)
b1011000 0
b1011100 1
b1011100 F
b1011100 G
b1011000 J
b0 K
#210000
0!
0)
#215000
1!
b1011100 $
1)
b1011100 0
b1100000 1
b1100000 F
b1100000 G
b1011100 J
b0 K
#220000
0!
0)
#225000
1!
b1100000 $
1)
b1100000 0
b1100100 1
b1100100 F
b1100100 G
b1100000 J
b0 K
#230000
0!
0)
#235000
1!
b1100100 $
1)
b1100100 0
b1101000 1
b1101000 F
b1101000 G
b1100100 J
b0 K
#240000
0!
0)
#245000
1!
b1101000 $
1)
b1101000 0
b1101100 1
b1101100 F
b1101100 G
b1101000 J
b0 K
#250000
0!
0)
#255000
1!
b1101100 $
1)
b1101100 0
b1110000 1
b1110000 F
b1110000 G
b1101100 J
b0 K
#260000
0!
0)
#265000
1!
b1110000 $
1)
b1110000 0
b1110100 1
b1110100 F
b1110100 G
b1110000 J
b0 K
#270000
0!
0)
#275000
1!
b1110100 $
1)
b1110100 0
b1111000 1
b1111000 F
b1111000 G
b1110100 J
b0 K
#280000
0!
0)
#285000
1!
b1111000 $
1)
b1111000 0
b1111100 1
b1111100 F
b1111100 G
b1111000 J
b0 K
#290000
0!
0)
#295000
1!
b1111100 $
1)
b1111100 0
b10000000 1
b10000000 F
b10000000 G
b1111100 J
b0 K
#300000
0!
0)
#305000
1!
b10000000 $
1)
b10000000 0
b10000100 1
b10000100 F
b10000100 G
b10000000 J
b0 K
#310000
0!
0)
#315000
1!
b10000100 $
1)
b10000100 0
b10001000 1
b10001000 F
b10001000 G
b10000100 J
b0 K
#320000
0!
0)
#325000
1!
b10001000 $
1)
b10001000 0
b10001100 1
b10001100 F
b10001100 G
b10001000 J
b0 K
#330000
0!
0)
#335000
1!
b10001100 $
1)
b10001100 0
b10010000 1
b10010000 F
b10010000 G
b10001100 J
b0 K
#340000
0!
0)
#345000
1!
b10010000 $
1)
b10010000 0
b10010100 1
b10010100 F
b10010100 G
b10010000 J
b0 K
#350000
0!
0)
#355000
1!
b10010100 $
1)
b10010100 0
b10011000 1
b10011000 F
b10011000 G
b10010100 J
b0 K
#360000
0!
0)
#365000
1!
b10011000 $
1)
b10011000 0
b10011100 1
b10011100 F
b10011100 G
b10011000 J
b0 K
#370000
0!
0)
#375000
1!
b10011100 $
1)
b10011100 0
b10100000 1
b10100000 F
b10100000 G
b10011100 J
b0 K
#380000
0!
0)
#385000
1!
b10100000 $
1)
b10100000 0
b10100100 1
b10100100 F
b10100100 G
b10100000 J
b0 K
#390000
0!
0)
#395000
1!
b10100100 $
1)
b10100100 0
b10101000 1
b10101000 F
b10101000 G
b10100100 J
b0 K
#400000
0!
0)
#405000
1!
b10101000 $
1)
b10101000 0
b10101100 1
b10101100 F
b10101100 G
b10101000 J
b0 K
#410000
0!
0)
#415000
1!
b10101100 $
1)
b10101100 0
b10110000 1
b10110000 F
b10110000 G
b10101100 J
b0 K
#420000
0!
0)
#425000
1!
b10110000 $
1)
b10110000 0
b10110100 1
b10110100 F
b10110100 G
b10110000 J
b0 K
#430000
0!
0)
#435000
1!
b10110100 $
1)
b10110100 0
b10111000 1
b10111000 F
b10111000 G
b10110100 J
b0 K
#440000
0!
0)
#445000
1!
b10111000 $
1)
b10111000 0
b10111100 1
b10111100 F
b10111100 G
b10111000 J
b0 K
#450000
0!
0)
#455000
1!
b10111100 $
1)
b10111100 0
b11000000 1
b11000000 F
b11000000 G
b10111100 J
b0 K
#460000
0!
0)
#465000
1!
b11000000 $
1)
b11000000 0
b11000100 1
b11000100 F
b11000100 G
b11000000 J
b0 K
#470000
0!
0)
#475000
1!
b11000100 $
1)
b11000100 0
b11001000 1
b11001000 F
b11001000 G
b11000100 J
b0 K
#480000
0!
0)
#485000
1!
b11001000 $
1)
b11001000 0
b11001100 1
b11001100 F
b11001100 G
b11001000 J
b0 K
#490000
0!
0)
#495000
1!
b11001100 $
1)
b11001100 0
b11010000 1
b11010000 F
b11010000 G
b11001100 J
b0 K
#500000
0!
0)
#505000
1!
b11010000 $
1)
b11010000 0
b11010100 1
b11010100 F
b11010100 G
b11010000 J
b0 K
